CHANGELOG.txt
LICENSE.txt
MANIFEST.in
README.md
setup.cfg
setup.py
./cIMZ/segment.cpp
./cIMZ/src/imageregion.cpp
./cIMZ/src/srm.cpp
cIMZ/build_steps.sh
cIMZ/segment.cpp
cIMZ/src/imageregion.cpp
cIMZ/src/imageregion.h
cIMZ/src/srm.cpp
cIMZ/src/srm.h
pIMZ/__init__.py
pIMZ/comparative.py
pIMZ/hubmap_downloader.py
pIMZ/imzml.py
pIMZ/parser.py
pIMZ/regions.py
pIMZ.egg-info/PKG-INFO
pIMZ.egg-info/SOURCES.txt
pIMZ.egg-info/dependency_links.txt
pIMZ.egg-info/entry_points.txt
pIMZ.egg-info/not-zip-safe
pIMZ.egg-info/requires.txt
pIMZ.egg-info/top_level.txt
pIMZ/tablefilter/tablefilter.js
pIMZ/tablefilter/tablefilter.js.map
pIMZ/tablefilter/tf-1-d93e97e989b71a9f7e7e.js
pIMZ/tablefilter/tf-1-d93e97e989b71a9f7e7e.js.map
pIMZ/tablefilter/style/colsVisibility.css
pIMZ/tablefilter/style/filtersVisibility.css
pIMZ/tablefilter/style/tablefilter.css
pIMZ/tablefilter/style/themes/blank.png
pIMZ/tablefilter/style/themes/btn_clear_filters.png
pIMZ/tablefilter/style/themes/btn_filter.png
pIMZ/tablefilter/style/themes/btn_first_page.gif
pIMZ/tablefilter/style/themes/btn_last_page.gif
pIMZ/tablefilter/style/themes/btn_next_page.gif
pIMZ/tablefilter/style/themes/btn_previous_page.gif
pIMZ/tablefilter/style/themes/downsimple.png
pIMZ/tablefilter/style/themes/icn_clp.png
pIMZ/tablefilter/style/themes/icn_exp.png
pIMZ/tablefilter/style/themes/icn_filter.gif
pIMZ/tablefilter/style/themes/icn_filterActive.gif
pIMZ/tablefilter/style/themes/upsimple.png
pIMZ/tablefilter/style/themes/default/default.css
pIMZ/tablefilter/style/themes/default/images/bg_infDiv.jpg
pIMZ/tablefilter/style/themes/default/images/bg_th.jpg
pIMZ/tablefilter/style/themes/default/images/btn_eraser.gif
pIMZ/tablefilter/style/themes/default/images/btn_first_page.gif
pIMZ/tablefilter/style/themes/default/images/btn_last_page.gif
pIMZ/tablefilter/style/themes/default/images/btn_next_page.gif
pIMZ/tablefilter/style/themes/default/images/btn_over_eraser.gif
pIMZ/tablefilter/style/themes/default/images/btn_over_first_page.gif
pIMZ/tablefilter/style/themes/default/images/btn_over_last_page.gif
pIMZ/tablefilter/style/themes/default/images/btn_over_next_page.gif
