Metadata-Version: 2.1
Name: pIMZ
Version: 1.0a0
Summary: pIMZ: an integrative framework for imaging mass spectrometry analysis
Home-page: https://github.com/mjoppich/pIMZ
Author: Markus Joppich
Author-email: pIMZ@compbio.cc
License: MIT
Keywords: IMS MSI imaging mass-spectrometry interactive integrative
Platform: UNKNOWN
Classifier: Development Status :: 3 - Alpha
Classifier: Intended Audience :: Developers
Classifier: Programming Language :: Python
Classifier: Programming Language :: Python :: 3 :: Only
Classifier: Programming Language :: Python :: 3.8
Classifier: Programming Language :: Python :: 3.9
Classifier: Topic :: Scientific/Engineering :: Bio-Informatics
Classifier: Topic :: Scientific/Engineering :: Medical Science Apps.
Requires-Python: >=3.8
